[
  {
    "name": "admin",
    "path": "/admin",
    "component": "C:\\\\Users\\\\Felipe\\\\Documents\\\\sistema\\\\budget_frontend\\\\pages\\\\admin.vue",
    "chunkName": "pages/admin",
    "_name": "_3a7e2a19"
  },
  {
    "name": "budget",
    "path": "/budget",
    "component": "C:\\\\Users\\\\Felipe\\\\Documents\\\\sistema\\\\budget_frontend\\\\pages\\\\budget.vue",
    "chunkName": "pages/budget",
    "_name": "_747a0c2a"
  },
  {
    "name": "login",
    "path": "/login",
    "component": "C:\\\\Users\\\\Felipe\\\\Documents\\\\sistema\\\\budget_frontend\\\\pages\\\\login.vue",
    "chunkName": "pages/login",
    "_name": "_5a930d9a"
  },
  {
    "name": "index",
    "path": "/",
    "component": "C:\\\\Users\\\\Felipe\\\\Documents\\\\sistema\\\\budget_frontend\\\\pages\\\\index.vue",
    "chunkName": "pages/index",
    "_name": "_090ed61c"
  }
]
